_km_omp
multiresolcp
