Metadata-Version: 1.1
Name: multiresolcp
Version: 0.0.6
Summary: KM algorithm for networks induced by a one-mode projection of networks
Home-page: https://github.com/skojaku/multiresolcp
Author: Sadamori Kojaku
Author-email: freesailing4046@gmail.com
License: MIT
Keywords: network core-periphery structure bipartite network
Platform: UNKNOWN
Classifier: Development Status :: 3 - Alpha
Classifier: Intended Audience :: Science/Research
Classifier: Topic :: Software Development
Classifier: License :: OSI Approved :: MIT License
Classifier: Programming Language :: Python :: 3.4
Classifier: Programming Language :: Python :: 3.5
Classifier: Programming Language :: Python :: 3.6
